[
  {
    "slug": "2025-06-26-test-post",
    "title": "Test Post",
    "date": "2025-06-26T23:28:00.000Z",
    "excerpt": "This is an excerpt.",
    "tags": [
      "Doula"
    ],
    "author": "Greg",
    "published": true,
    "content": "Cheese\n",
    "image": "/images/blog/photo-1584515933487-779824d29309.jpeg"
  },
  {
    "slug": "2025-01-01-welcome-to-my-blog",
    "title": "Welcome to My Blog",
    "date": "2025-01-01T10:00:00.000Z",
    "excerpt": "Welcome to my doula blog where I share insights about birth, pregnancy, and supporting families through their journey.",
    "tags": [
      "welcome",
      "introduction",
      "doula care"
    ],
    "author": "Esther",
    "published": true,
    "content": "\n# Welcome to My Blog\n\nI'm so excited to share this space with you! This blog will be a place where I can share insights, tips, and stories from my journey as a doula.\n\n## What You Can Expect\n\nHere you'll find:\n- Birth stories and experiences\n- Pregnancy and postpartum tips\n- Information about doula services\n- Resources for expecting families\n- Personal reflections on supporting families\n\n## My Mission\n\nAs a doula, my mission is to provide compassionate, non-judgmental support to families during one of the most transformative times in their lives. Through this blog, I hope to extend that support to a wider community.\n\nThank you for joining me on this journey. I look forward to sharing more with you soon!\n\nWith love and light,\nSarah\n"
  }
]